WrenchCL/__init__.py
WrenchCL/Connect/AwsClientHub.py
WrenchCL/Connect/Lambda.py
WrenchCL/Connect/ProcessingTracker.py
WrenchCL/Connect/RdsServiceGateway.py
WrenchCL/Connect/S3ServiceGateway.py
WrenchCL/Connect/__init__.py
WrenchCL/Connect/_Internal/_ConfigurationManager.py
WrenchCL/Connect/_Internal/_SshTunnelManager.py
WrenchCL/Connect/_Internal/__init__.py
WrenchCL/Connect/_Internal/_boto_cache.py
WrenchCL/Decorators/Deprecated.py
WrenchCL/Decorators/Retryable.py
WrenchCL/Decorators/SingletonClass.py
WrenchCL/Decorators/Synchronized.py
WrenchCL/Decorators/__init__.py
WrenchCL/Exceptions/Arguments.py
WrenchCL/Exceptions/ExceptionSuggestor.py
WrenchCL/Exceptions/Initializations.py
WrenchCL/Exceptions/Misc.py
WrenchCL/Exceptions/__init__.py
WrenchCL/Exceptions/_internal.py
WrenchCL/Tools/Coalesce.py
WrenchCL/Tools/FetchMetaData.py
WrenchCL/Tools/FileTyper.py
WrenchCL/Tools/Image2B64.py
WrenchCL/Tools/JsonParser.py
WrenchCL/Tools/JsonSerializer.py
WrenchCL/Tools/MaybeMonad.py
WrenchCL/Tools/StandardizeNone.py
WrenchCL/Tools/TypeChecker.py
WrenchCL/Tools/__init__.py
WrenchCL/Tools/truncate_display.py
WrenchCL/_Internal/_ExceptionSuggestor.py
WrenchCL/_Internal/_MockPandas.py
WrenchCL/_Internal/__init__.py
WrenchCL/_Internal/_custom_types.py
WrenchCL/_Internal/cLogger.py
WrenchCL/_Internal/Logging/ColorService.py
WrenchCL/_Internal/Logging/DataClasses.py
WrenchCL/_Internal/Logging/DatadogTraceInjectionFilter.py
WrenchCL/_Internal/Logging/Formatters.py
WrenchCL/_Internal/Logging/LogManagers.py
WrenchCL/_Internal/Logging/LoggerConfigState.py
WrenchCL/_Internal/Logging/MarkupHandlers.py
WrenchCL/_Internal/Logging/MessageProcessors.py
WrenchCL/_Internal/Logging/__init__.py
WrenchCL/_Internal/Logging/logging_utils.py
WrenchCL/_Internal/Logging/Api/__init__.py
WrenchCL/_Internal/Logging/Api/base_logger.py
WrenchCL/_Internal/Logging/Api/internal_api.py
WrenchCL/_Internal/Logging/Api/managed_loggers.py
WrenchCL/_Internal/Logging/Api/stream_manager.py
wrenchcl-5.0.0.dist-info/METADATA
wrenchcl-5.0.0.dist-info/WHEEL
wrenchcl-5.0.0.dist-info/licenses/LICENSE
wrenchcl-5.0.0.dist-info/RECORD
