Metadata-Version: 2.4
Name: WrenchCL
Version: 5.0.0
Summary: Comprehensive library for seamless integration with AWS, OpenAI, and utility tools.
Project-URL: Homepage, https://github.com/WrenchAI/WrenchCL
Project-URL: Repository, https://github.com/WrenchAI/WrenchCL
Project-URL: Bug Tracker, https://github.com/WrenchAI/WrenchCL/issues
Project-URL: Documentation, https://wrenchcl.readthedocs.io/en/latest
Project-URL: Changelog, https://github.com/WrenchAI/WrenchCL/blob/main/CHANGELOG.md
Project-URL: PyPI, https://pypi.org/project/WrenchCL/
Project-URL: Author GitHub, https://github.com/Kydoimos97
Project-URL: Author PyPI, https://pypi.org/user/Kydoimos97/
Project-URL: Maintainer GitHub, https://github.com/dalmad2
Project-URL: Maintainer PyPI, https://pypi.org/user/sot232/
Author-email: Willem van der Schans <willem@wrench.ai>
Maintainer-email: Willem van der Schans <willem@wrench.ai>, Jeong Kim <jeong@wrench.ai>
License: #  Copyright (c) $YEAR$. Copyright (c) $YEAR$ Wrench.AI., Willem van der Schans, Jeong Kim
License-File: LICENSE
Keywords: aws,cloud,database,openai,sdk,utilities
Classifier: Intended Audience :: Developers
Classifier: License :: OSI Approved :: MIT License
Classifier: Operating System :: OS Independent
Classifier: Programming Language :: Python :: 3
Classifier: Programming Language :: Python :: 3.11
Requires-Python: >=3.11
Requires-Dist: ansi2txt<1.0.0,>=0.2.0
Requires-Dist: filetype<2.0,>=1.2
Requires-Dist: ftfy<7.0.0,>=6.3.1
Requires-Dist: python-dotenv<2.0,>=1.0
Requires-Dist: requests<3.0,>=2.32
